README.txt
setup.py
ctviewer/CTViewer.py
ctviewer/__init__.py
ctviewer.egg-info/PKG-INFO
ctviewer.egg-info/SOURCES.txt
ctviewer.egg-info/dependency_links.txt
ctviewer.egg-info/requires.txt
ctviewer.egg-info/top_level.txt