Metadata-Version: 2.1
Name: ctviewer
Version: 1.0.0
Summary: Interactive utility to view 3D CT images in ipython notebooks
Home-page: https://github.com/vibhuagrawal14/ctviewer
Author: Vibhu Agrawal
Author-email: vibhu.agrawal14@gmail.com
License: MIT
Platform: UNKNOWN
Classifier: License :: OSI Approved :: MIT License
Classifier: Programming Language :: Python
Classifier: Programming Language :: Python :: 3
Classifier: Programming Language :: Python :: Implementation :: CPython
Classifier: Programming Language :: Python :: Implementation :: PyPy
